server.py
mseep_yugabytedb_mcp_server-1.0.3.dist-info/licenses/LICENSE
mseep_yugabytedb_mcp_server-1.0.3.dist-info/METADATA
mseep_yugabytedb_mcp_server-1.0.3.dist-info/WHEEL
mseep_yugabytedb_mcp_server-1.0.3.dist-info/top_level.txt
mseep_yugabytedb_mcp_server-1.0.3.dist-info/RECORD
